odoo/addons/partner_email_history/LICENSE
odoo/addons/partner_email_history/README.rst
odoo/addons/partner_email_history/__init__.py
odoo/addons/partner_email_history/__manifest__.py
odoo/addons/partner_email_history/images/screen.png
odoo/addons/partner_email_history/models/__init__.py
odoo/addons/partner_email_history/models/res_partner.py
odoo/addons/partner_email_history/readme/CONTRIBUTORS.md
odoo/addons/partner_email_history/readme/DESCRIPTION.md
odoo/addons/partner_email_history/readme/USAGE.md
odoo/addons/partner_email_history/static/description/icon.png
odoo/addons/partner_email_history/static/description/index.html
odoo/addons/partner_email_history/tests/TEST_INSTRUCTIONS.rst
odoo/addons/partner_email_history/views/res_partner_views.xml
odoo_addon_partner_email_history-18.0.1.0.0.dist-info/METADATA
odoo_addon_partner_email_history-18.0.1.0.0.dist-info/WHEEL
odoo_addon_partner_email_history-18.0.1.0.0.dist-info/top_level.txt
odoo_addon_partner_email_history-18.0.1.0.0.dist-info/RECORD
